OhMyRunPod/__init__.py
OhMyRunPod/main.py
OhMyRunPod/ui.py
OhMyRunPod/modules/__init__.py
OhMyRunPod/modules/comfyui/__init__.py
OhMyRunPod/modules/comfyui/comfyui.py
OhMyRunPod/modules/file_transfer/__init__.py
OhMyRunPod/modules/file_transfer/file_transfer.py
OhMyRunPod/modules/pod_info/__init__.py
OhMyRunPod/modules/pod_info/pod_info.py
OhMyRunPod/modules/ssh_setup/__init__.py
OhMyRunPod/modules/ssh_setup/ssh_setup.py
OhMyRunPod/modules/tailscale_setup/__init__.py
OhMyRunPod/modules/tailscale_setup/tailscale_setup.py
ohmyrunpod-0.6.2.dist-info/licenses/LICENSE
ohmyrunpod-0.6.2.dist-info/METADATA
ohmyrunpod-0.6.2.dist-info/WHEEL
ohmyrunpod-0.6.2.dist-info/entry_points.txt
ohmyrunpod-0.6.2.dist-info/top_level.txt
ohmyrunpod-0.6.2.dist-info/RECORD
